topsis_package/__init__.py
topsis_package/topsis.py
topsis_Inderjeet_101803689-1.0.0.dist-info/License.txt
topsis_Inderjeet_101803689-1.0.0.dist-info/METADATA
topsis_Inderjeet_101803689-1.0.0.dist-info/WHEEL
topsis_Inderjeet_101803689-1.0.0.dist-info/top_level.txt
topsis_Inderjeet_101803689-1.0.0.dist-info/RECORD
