Metadata-Version: 2.1
Name: topsis-Inderjeet-101803689
Version: 1.0.0
Summary: It is package which is used to find best among the value using mathematical model(topsis)
Home-page: https://github.com/inder052000/topsis_package
Author: Inderjeet Singh
Author-email: inder052000@gmail.com
License: UNKNOWN
Platform: UNKNOWN
Classifier: Programming Language :: Python :: 3
Classifier: License :: OSI Approved :: MIT License
Classifier: Operating System :: OS Independent
Requires-Python: >=3.6
Requires-Dist: pandas
Requires-Dist: numpy (==1.19.3)
